tickle/__init__.py
tickle/__main__.py
tickle/cli.py
tickle/config.py
tickle/detectors.py
tickle/git_utils.py
tickle/models.py
tickle/output.py
tickle/scanner.py
tickle_cli-0.3.0.dist-info/licenses/LICENSE
tickle_cli-0.3.0.dist-info/METADATA
tickle_cli-0.3.0.dist-info/WHEEL
tickle_cli-0.3.0.dist-info/entry_points.txt
tickle_cli-0.3.0.dist-info/top_level.txt
tickle_cli-0.3.0.dist-info/RECORD
