Metadata-Version: 2.4
Name: tickle-cli
Version: 0.3.0
Summary: Hierarchical visualization of developer tasks across code repositories
Author-email: Colin Brown <colinmakerofthings@gmail.com>
License: MIT
Project-URL: Homepage, https://github.com/colinmakerofthings/tickle-cli
Project-URL: Repository, https://github.com/colinmakerofthings/tickle-cli
Project-URL: Issues, https://github.com/colinmakerofthings/tickle-cli/issues
Keywords: todo,fixme,task,git-blame,code-analysis,developer-tools,visualization,tree-view
Classifier: Development Status :: 4 - Beta
Classifier: Environment :: Console
Classifier: Intended Audience :: Developers
Classifier: License :: OSI Approved :: MIT License
Classifier: Operating System :: OS Independent
Classifier: Programming Language :: Python :: 3
Classifier: Programming Language :: Python :: 3.10
Classifier: Programming Language :: Python :: 3.11
Classifier: Programming Language :: Python :: 3.12
Classifier: Programming Language :: Python :: 3.13
Classifier: Topic :: Software Development :: Quality Assurance
Classifier: Topic :: Software Development :: Documentation
Classifier: Topic :: Utilities
Requires-Python: >=3.10
License-File: LICENSE
Requires-Dist: tomli>=2.0.0; python_version < "3.11"
Requires-Dist: colorama>=0.4.6
Requires-Dist: rich>=13.0.0
Requires-Dist: humanize>=4.0.0
Provides-Extra: dev
Requires-Dist: pytest>=7.0; extra == "dev"
Requires-Dist: pytest-cov>=4.0; extra == "dev"
Requires-Dist: ruff>=0.1.0; extra == "dev"
Dynamic: license-file
